setup.py
imgur4blog/__init__.py
imgur4blog/imgur4blog.py
imgur4blog.egg-info/PKG-INFO
imgur4blog.egg-info/SOURCES.txt
imgur4blog.egg-info/dependency_links.txt
imgur4blog.egg-info/entry_points.txt
imgur4blog.egg-info/not-zip-safe
imgur4blog.egg-info/pbr.json
imgur4blog.egg-info/requires.txt
imgur4blog.egg-info/top_level.txt