Metadata-Version: 1.0
Name: imgur4blog
Version: 1.0
Summary: 写博客用的imgur图传
Home-page: https://github.com/wzyuliyang/imgur4blog
Author: wzyuliyang
Author-email: wzyuliyang911@gmail.com
License: MIT License
Keywords: python qiniu
Platform: UNKNOWN
